Workbook
Name IQ_CH: 110000
Name IQ_CQ: 5000
Name IQ_CY: 10000
Name IQ_DAILY: 500000
Name IQ_FH: 100000
Name IQ_FQ: 500
Name IQ_FY: 1000
Name IQ_LTM: 2000
Name IQ_MONTH: 15000
Name IQ_NTM: 6000
Name IQ_WEEK: 50000
Name IQ_YTD: 3000

Sheet cover
B2: #VALUE!
B3: One of the cheapest gene therapies in history with solid value proposition
B5: Price | C5: {=_FV(B2,"Price")} -> 5.07 | E5: risk adjusted net present value
B6: Shares | C6: 52.4 | F6: ='risk adjusted post approval '!F104 -> Equity Value | H6: ='risk adjusted post approval '!G104 -> per share
B7: MC | C7: =C5*C6 -> 265.668 | E7: ='risk adjusted post approval '!E105 -> r= 7.61% | F7: ='risk adjusted post approval '!F105 -> 840.02572 | H7: ='risk adjusted post approval '!G105 -> 17.320118
B8: Cash & ST | C8: 207.1 | E8: ='risk adjusted post approval '!E106 -> r= 15% | F8: ='risk adjusted post approval '!F106 -> 640.30378 | H8: ='risk adjusted post approval '!G106 -> 13.20214
B9: Debt | C9: 24.1 | E9: ='risk adjusted post approval '!E107 -> r= 20% | F9: ='risk adjusted post approval '!F107 -> 552.00831 | H9: ='risk adjusted post approval '!G107 -> 11.381615
B10: EV | C10: =C7+C9-C8 -> 82.668
E11: ='risk adjusted post approval '!E109 -> Risk adjusted | F11: ='risk adjusted post approval '!F109 -> Equity value | H11: ='risk adjusted post approval '!G109 -> per share
B12: model estimates… | E12: ='risk adjusted post approval '!E110 -> r= 7.61% | F12: ='risk adjusted post approval '!F110 -> 558.95352 | H12: ='risk adjusted post approval '!G110 -> 11.524815
B13: Peak Sales | C13: 688 | D13: =C10/C13 -> 0.12015698 | E13: ='risk adjusted post approval '!E111 -> r= 15% | F13: ='risk adjusted post approval '!F111 -> 442.74332 | H13: ='risk adjusted post approval '!G111 -> 9.1287282
B14: 3Y Fwd Sales | C14: 290 | D14: =C10/C14 -> 0.28506207 | E14: ='risk adjusted post approval '!E112 -> r= 20% | F14: ='risk adjusted post approval '!F112 -> 391.53054 | H14: ='risk adjusted post approval '!G112 -> 8.0727947
B15: Cumulative 10Y | C15: =SUM('risk adjusted post approval '!F39:P39) -> 1920.0372
B16: EV/ c. 10y | C16: =C10/C15 -> 0.043055416
B18: Catalyst | C18: FY 2025
B20: EV @ 0.15x c.10y | C20: =C15*0.15 -> 288.00558
B21: Cash | C21: =C8 -> 207.1
B22: Debt | C22: =C9 -> 24.1
B23: FV | C23: =C20+C21-C22 -> 471.00558
C24: =C23/C6 -> 8.9886561
B26: Developer | C26: Owner | D26: Therapy | E26: Market | F26: Patients | G26: Price | H26: Opportunity $B | I26: Peak Sales | J26: MC/EV | K26: Peak Sales Multiple | L26: Opportunity Multiple | M26: Notes
A27: acq. | B27: AveXis | C27: Novartis | D27: Zolgensma | E27: spinal muscular atrophy | F27: 10000 | G27: 2100000 | H27: =F27*G27/1000000000 -> 21 | I27: 1300 | J27: 8700 | K27: =J27/I27 -> 6.6923077 | L27: =J27/1000/H27 -> 0.41428571
A28: acq. | B28: BioVex | C28: Amgen | D28: Imlygic | E28: melanoma | H28: =F28*G28/1000000000 -> 0 | I28: 200 | J28: 1000 | K28: =J28/I28 -> 5 | M28: (Bad comparison, ignore ) This was acquired in 2011 for up to $1B (including milestones, which were achieved) with peak sales potential of $200. Approval in 2015. Did not reach peak sales (realised 100-150M)
A29: > | B29: Krystal | C29: Krystal | D29: Vyjuvek | E29: DEB | F29: 4000 | G29: 600000 | H29: =F29*G29/1000000000 -> 2.4 | I29: 900 | J29: 4000 | K29: =J29/I29 -> 4.4444444 | L29: =J29/1000/H29 -> 1.6666667
A30: acq. | B30: Spark Tx | C30: Spark Tx (Roche) | D30: Luxturna | E30: Leber congenital amaurosis | F30: 3000 | G30: 850000 | H30: =F30*G30/1000000000 -> 2.55 | I30: 750 | J30: 4300 | K30: =J30/I30 -> 5.7333333 | L30: =J30/1000/H30 -> 1.6862745 | M30: Bought for $4.3B in 2019. Had estimated peak sales of $350-750, lifetime opportunity of $1-3B. Never realised this, was a miserable failure
A31: > | B31: UCL | C31: Autolus | D31: Aucatzyl | E31: ALL | F31: 1000 | G31: 525000 | H31: =F31*G31/1000000000 -> 0.525 | I31: 300 | J31: 322 | K31: =J31/I31 -> 1.0733333 | L31: =J31/1000/H31 -> 0.61333333 | M31: Note: I met the CEO at UBS. 6100 ALL diagnoses. 50% adults --> 3000. 75% B-cell precursor --> 2250. r/r 50% --> 1100 patients per year. --> $500M in peak sales. WB estimates $300 (public)
A32: > | B32: SRPT | C32: SRPT | D32: Elevidys | E32: DMD | F32: 6000 | G32: 3200000 | H32: =F32*G32/1000000000 -> 19.2 | I32: 2500 | J32: 2000 | K32: =J32/I32 -> 0.8 | L32: =J32/1000/H32 -> 0.10416667 | M32: Even after all the problems and associated risks, we are trading at more than 2x the Abeona multple. Also, we have been very generous with SRPT revenue forecast
A33: acq | B33: BMS & 2seventy | C33: BMS | D33: Abecma | E33: Multiple myeloma | F33: 127000 | G33: =419500 -> 419500 | H33: =F33*G33/1000000000 -> 53.2765 | I33: 224 | J33: =4.75*57.1-184 -> 87.225 | K33: =J33/I33 -> 0.38939732 | L33: =J33/1000/H33 -> 0.0016372134 | M33: (CAR-T) Peak sales estimate of $224M (2029) is from financial advisor (GS) during acquisition for valuation for $4.75 per share, 57.1M shares, Cash & ST of $184 at the time of acq.
B34: Abeona | C34: Abeona | D34: Zevaskyn | E34: RDEB | F34: 765 | G34: 3200000 | H34: =F34*G34/1000000000 -> 2.448 | I34: 688 | J34: =$C$10 -> 82.668 | K34: =J34/I34 -> 0.12015698 | L34: =J34/1000/H34 -> 0.033769608 | M34: risk adjusted post approval '!A1
A35: x | B35: Ferring | C35: Ferring | D35: Adstiladrin | E35: bladder cancer | F35: 15000 | G35: 240000 | H35: =F35*G35/1000000000 -> 3.6 | I35: 1400
A36: x | B36: uniQure | C36: uniQure | D36: Glybera | E36: LPD | K36: Median | L36: =MEDIAN(L27:L34) -> 0.41428571
A37: x | B37: Kite Pharma | C37: Gilead | D37: Yescarta | E37: B cell lymphoma
A38: x | B38: bluebird bio | C38: bluebird bio | D38: Zynteglo | E38: Beta thalassemia
A39: x | B39: Kite Pharma | C39: Gilead | D39: Tecartus | E39: Mantle cell lymphoma + ALL
A40: x | B40: Human Stem cell institute | D40: Neovasculgen | E40: Peripheral artery disease
A41: x | B41: JNJ | C41: JNJ | D41: Carvykti | E41: Multiple myeloma
A42: x | B42: bluebird bio | C42: bluebird bio | D42: Skysona | E42: adrenoleukodystorphy
A43: x | B43: uniQure | C43: CSL Behring | D43: Hemgenix | E43: hemophilia B
B44: Vertex & CRISPR | C44: Vertex & CRISPR | D44: Casgevy | E44: sickle cell
A45: x | B45: bluebird bio | C45: bluebird bio | D45: Lyfgenia | E45: sickle cell
B46: Novartis | C46: Novartis | D46: Kymriah | E46: b cell lymphoblastic lymphoma
B47: BioMarin | C47: BioMarin | D47: Roctavian | E47: hemo A

Sheet model 
A1: Research
B3: RDEB All | C3: Prevalence / mn | D3: Incidence /mn | E3: US pop mn | F3: Patient pop | G3: Notes
B4: Eichstadt et al (2019) | C4: =12562/340 -> 36.947059 | D4: 95 | E4: 340 | F4: =C4*E4 -> 12562 | G4: Unreliable genetic model
B5: Prop. Claims analysis (Abeona) | C5: =750/E5 -> 2.2058824 | D5: NA | E5: 340 | F5: 750 | G5: Method unavailable
A6: > | B6: Fine et al | C6: 1.35 | D6: 3.05 | E6: 340 | F6: =C6*E6 -> 459 | G6: NEBR data, most commonly cited
A7: > | B7: Baardman et al | C7: 2.1 | D7: 5.5 | E7: 340 | F7: =E7*C7 -> 714 | G7: Dutch EB registry
B8: Kim et al | E8: 340
A9: > | B9: Petrof et al | C9: 3.3 | D9: 8.1 | E9: 340 | F9: =C9*E9 -> 1122 | G9: NHS England and Wales
B10: Average | C10: =AVERAGE(C6:C9) -> 2.25 | D10: =AVERAGE(D6:D9) -> 5.55 | F10: =AVERAGE(F6:F9) -> 765
B12: RDEB patient "churn rate" | C12: =(D10*3.6)/F10 -> 0.026117647
B13: Implied life expectancy | C13: =1/C12 -> 38.288288
B14: Assuming 3.6 million live births
I15: (approval)
B16: Competition | C16: Vyjuvek | E16: #VALUE! | H16: KRYS uptake | I16: Q2 2023 | J16: Q3 2023 | K16: Q4 2023 | L16: Q1 2024 | M16: Q2 2024 | N16: Q3 2024 | O16: Q4 2024
B17: Marketing auth holder | C17: KRYS | E17: MC | F17: {=_FV(E16,"Market cap",TRUE)/1000000} -> 8083.6386 | G17: M | H17: Revenue | J17: 8.6 | K17: 42.1 | L17: 45.3 | M17: 70.3 | N17: 83.8 | O17: 91.1
B18: annualised sales (ASP) | C18: =91.1 * 4 -> 364.4 | E18: Cash | F18: 724.76 | G18: bpc 11.09.25 | H18: Patients treated | J18: =J17*1000000/($F$21/4) -> 68.690967 | K18: =K17*1000000/($F$21/4) -> 336.26624 | L18: =L17*1000000/($F$21/4) -> 361.82567 | M18: =M17*1000000/($F$21/4) -> 561.50872 | N18: =N17*1000000/($F$21/4) -> 669.33756 | O18: =O17*1000000/($F$21/4) -> 727.64501
B19: Sales (retail) | C19: =C18*1.26 -> 459.144 | E19: EV | F19: =F17-F18 -> 7358.8786 | G19: M | H19: patient pop | J19: =$C$23 -> 1108.4 | K19: =$C$23 -> 1108.4 | L19: =$C$23 -> 1108.4 | M19: =$C$23 -> 1108.4 | N19: =$C$23 -> 1108.4 | O19: =$C$23 -> 1108.4
B20: Pricing (list) - patient year | C20: 631000 | E20: Peak sales | F20: =F21*F22/1000000 -> 1001.5873 | G20: M | H20: % of peak | J20: =J18/J19 -> 0.061973084 | K20: =K18/K19 -> 0.30337987 | L20: =L18/L19 -> 0.32643962 | M20: =M18/M19 -> 0.50659393 | N20: =N18/N19 -> 0.60387726 | O20: =O18/O19 -> 0.65648232
B21: Patients | C21: =C19*1000000/C20 -> 727.64501 | E21: ASP/patient y | F21: =C18*1000000/C21 -> 500793.65 | G21: $ | O21: quick uptake
B22: Peak patients | C22: 2000 | D22: RDEB + DDEB | E22: Peak patients | F22: =C22 -> 2000
A23: ??? | B23: DEB prevalence (JD Fine) | C23: =340*3.26 -> 1108.4 | E23: EV-Peak sales | F23: =F19/F20 -> 7.3472164 | G23: x
B24: RDEB | C24: 765
A26: Model
C27: Notes | D27: 2022 | E27: 2023 | F27: 2024 | Q27: check patent expiry date ...
B28: US population | G28: 2025 | H28: =G28+1 -> 2026 | I28: =H28+1 -> 2027 | J28: =I28+1 -> 2028 | K28: =J28+1 -> 2029 | L28: =K28+1 -> 2030 | M28: =L28+1 -> 2031 | N28: =M28+1 -> 2032 | O28: =N28+1 -> 2033 | ... X28: =W28+1 -> 2042
B29: Prevalence | C29: [1] | G29: 340 | H29: 340 | I29: 340 | J29: 340 | K29: 340 | L29: 340 | M29: 340 | N29: 340 | O29: 340 | P29: 340 | Q29: 340 | R29: 340 | S29: 340 | T29: 340 | U29: 340 | V29: 340 | W29: 340 | X29: 340
B30: Patient population | G30: =AVERAGE($C$9,$C$7,$C$6) -> 2.25 | H30: =AVERAGE($C$9,$C$7,$C$6) -> 2.25 | I30: =AVERAGE($C$9,$C$7,$C$6) -> 2.25 | J30: =AVERAGE($C$9,$C$7,$C$6) -> 2.25 | K30: =AVERAGE($C$9,$C$7,$C$6) -> 2.25 | L30: =AVERAGE($C$9,$C$7,$C$6) -> 2.25 | M30: =AVERAGE($C$9,$C$7,$C$6) -> 2.25 | N30: =AVERAGE($C$9,$C$7,$C$6) -> 2.25 | ... X30: =AVERAGE($C$9,$C$7,$C$6) -> 2.25
B31: US Live births | G31: =G29*G30 -> 765 | H31: =H29*H30 -> 765 | I31: =I29*I30 -> 765 | J31: =J29*J30 -> 765 | K31: =K29*K30 -> 765 | L31: =L29*L30 -> 765 | M31: =M29*M30 -> 765 | N31: =N29*N30 -> 765 | ... X31: =X29*X30 -> 765
B32: Incidence /mn | C32: [1] | G32: 3.6 | H32: 3.6 | I32: 3.6 | J32: 3.6 | K32: 3.6 | L32: 3.6 | M32: 3.6 | N32: 3.6 | O32: 3.6 | P32: 3.6 | Q32: 3.6 | R32: 3.6 | S32: 3.6 | T32: 3.6 | U32: 3.6 | V32: 3.6 | W32: 3.6 | X32: 3.6
B33: Incidence total | G33: 5.55 | H33: 5.55 | I33: 5.55 | J33: 5.55 | K33: 5.55 | L33: 5.55 | M33: 5.55 | N33: 5.55 | O33: 5.55 | P33: 5.55 | Q33: 5.55 | R33: 5.55 | S33: 5.55 | T33: 5.55 | U33: 5.55 | V33: 5.55 | W33: 5.55 | X33: 5.55
B34: BOP treatment opportunities | C34: [3] | G34: =G33*G32 -> 19.98 | H34: =H33*H32 -> 19.98 | I34: =I33*I32 -> 19.98 | J34: =J33*J32 -> 19.98 | K34: =K33*K32 -> 19.98 | L34: =L33*L32 -> 19.98 | M34: =M33*M32 -> 19.98 | N34: =N33*N32 -> 19.98 | ... X34: =X33*X32 -> 19.98
B35: treatments administered | G35: =G31*0.8*2 -> 1224 | H35: =G35-G36+H34*2*0.8 -> 1230.968 | I35: =H35-H36+I34*2*0.8 -> 1152.936 | J35: =I35-I36+J34*2*0.8 -> 984.904 | K35: =J35-J36+K34*2*0.8 -> 816.872 | L35: =K35-K36+L34*2*0.8 -> 648.84 | M35: =L35-L36+M34*2*0.8 -> 480.808 | N35: =M35-M36+N34*2*0.8 -> 312.776 | O35: =N35-N36+O34*2*0.8 -> 144.744 | ... X35: =W35-W36+X34*2*0.8 -> 31.968 | Y35: =SUM(G36:X36) -> 1767.456
B36: Price per treatment | C36: [5] | G36: 25 | H36: 110 | I36: 200 | J36: 200 | K36: 200 | L36: 200 | M36: 200 | N36: 200 | O36: =O35 -> 144.744 | P36: =P35 -> 31.968 | Q36: =Q35 -> 31.968 | R36: =R35 -> 31.968 | S36: =S35 -> 31.968 | T36: =T35 -> 31.968 | U36: =U35 -> 31.968 | V36: =V35 -> 31.968 | ... X36: =X35 -> 31.968
B37: Price (ASP) | G37: 1500000 | H37: =G37*1.02 -> 1530000 | I37: =H37*1.02 -> 1560600 | J37: =I37*1.02 -> 1591812 | K37: =J37*1.02 -> 1623648.2 | L37: =K37*1.02 -> 1656121.2 | M37: =L37*1.02 -> 1689243.6 | N37: =M37*1.02 -> 1723028.5 | O37: =N37*1.02 -> 1757489.1 | ... X37: =W37*1.02 -> 2100362.1
B38: Revenue | G38: =G37*0.74 -> 1110000 | H38: =H37*0.74 -> 1132200 | I38: =I37*0.74 -> 1154844 | J38: =J37*0.74 -> 1177940.9 | K38: =K37*0.74 -> 1201499.7 | L38: =L37*0.74 -> 1225529.7 | M38: =M37*0.74 -> 1250040.3 | N38: =N37*0.74 -> 1275041.1 | ... X38: =X37*0.74 -> 1554268
B39: COGS | C39: [6] | G39: =G36*G38/1000000 -> 27.75 | H39: =H36*H38/1000000 -> 124.542 | I39: =I36*I38/1000000 -> 230.9688 | J39: =J36*J38/1000000 -> 235.58818 | K39: =K36*K38/1000000 -> 240.29994 | L39: =L36*L38/1000000 -> 245.10594 | M39: =M36*M38/1000000 -> 250.00806 | N39: =N36*N38/1000000 -> 255.00822 | ... X39: =X36*X38/1000000 -> 49.686839
B40: Gross profit | G40: =G39*0.15 -> 4.1625 | H40: =H39*0.15 -> 18.6813 | I40: =I39*0.15 -> 34.64532 | J40: =J39*0.15 -> 35.338226 | K40: =K39*0.15 -> 36.044991 | L40: =L39*0.15 -> 36.765891 | M40: =M39*0.15 -> 37.501209 | N40: =N39*0.15 -> 38.251233 | ... X40: =X39*0.15 -> 7.4530258
G41: =G39-G40 -> 23.5875 | H41: =H39-H40 -> 105.8607 | I41: =I39-I40 -> 196.32348 | J41: =J39-J40 -> 200.24995 | K41: =K39-K40 -> 204.25495 | L41: =L39-L40 -> 208.34005 | M41: =M39-M40 -> 212.50685 | N41: =N39-N40 -> 216.75699 | ... X41: =X39-X40 -> 42.233813
B42: R&D | D42: 28.97 | E42: 31.09 | F42: 34.36
B43: General & Administrative | D43: 17.26 | E43: 19 | F43: 29.85 | G43: 5 | H43: 5 | I43: 5 | J43: 5 | K43: 5 | L43: 5 | M43: 5 | N43: 5 | O43: 5 | P43: 5 | Q43: 5 | R43: 5 | S43: 5 | T43: 5 | U43: 5 | V43: 5 | W43: 5 | X43: 5
B44: EBIT | G44: =136*1.5*0.225 -> 45.9 | H44: =136*1.5*0.225 -> 45.9 | I44: =136*1.5*0.225 -> 45.9 | J44: =J39*0.3 -> 70.676453 | K44: =K39*0.34 -> 81.701979 | L44: =L39*0.34 -> 83.336019 | M44: =M39*0.34 -> 85.002739 | N44: =N39*0.34 -> 86.702794 | O44: =O39*0.34 -> 64.003517 | P44: =P39*0.34 -> 14.418461 | Q44: =Q39*0.34 -> 14.70683 | R44: =R39*0.34 -> 15.000967 | ... X44: =X39*0.34 -> 16.893525
B45: Interest Income | D45: 0.431 | E45: 2.117 | F45: 4.25 | G45: =G41-G43-G44 -> -27.3125 | H45: =H41-H43-H44 -> 54.9607 | I45: =I41-I43-I44 -> 145.42348 | J45: =J41-J43-J44 -> 124.5735 | K45: =K41-K43-K44 -> 117.55297 | L45: =L41-L43-L44 -> 120.00403 | M45: =M41-M43-M44 -> 122.50411 | N45: =N41-N43-N44 -> 125.05419 | ... X45: =X41-X43-X44 -> 20.340288
B46: Interest Expense | F46: 4.208 | G46: 4 | H46: 4 | I46: 4 | J46: 4 | K46: 4 | L46: 4 | M46: 4 | N46: 4 | O46: 4 | P46: 4 | Q46: 4 | R46: 4 | S46: 4 | T46: 4 | U46: 4 | V46: 4 | W46: 4 | X46: 4
B47: Effective borrow rate | C47: [7] | F47: =F46/F62 -> 0.22194093 | G47: =G48*G62 -> 1.755 | H47: =H48*H62 -> 1.755 | I47: =I48*I62 -> 1.755 | J47: =J48*J62 -> 1.755 | K47: =K48*K62 -> 1.755 | L47: =L48*L62 -> 1.755 | M47: =M48*M62 -> 0 | N47: =N48*N62 -> 0 | ... X47: =X48*X62 -> 0
B48: EBT | G48: 0.135 | H48: 0.135 | I48: 0.135 | J48: 0.135 | K48: 0.135 | L48: 0.135 | M48: 0.135 | N48: 0.135 | O48: 0.135 | P48: 0.135 | Q48: 0.135 | R48: 0.135 | S48: 0.135 | T48: 0.135 | U48: 0.135 | V48: 0.135 | W48: 0.135 | X48: 0.135
B49: Tax | G49: =G45+G46-G47 -> -25.0675 | H49: =H45+H46-H47 -> 57.2057 | I49: =I45+I46-I47 -> 147.66848 | J49: =J45+J46-J47 -> 126.8185 | K49: =K45+K46-K47 -> 119.79797 | L49: =L45+L46-L47 -> 122.24903 | M49: =M45+M46-M47 -> 126.50411 | N49: =N45+N46-N47 -> 129.05419 | ... X49: =X45+X46-X47 -> 24.340288
B50: Net profit | G50: =IF(G49>0,G49*0.2,0) -> 0 | H50: =IF(H49>0,H49*0.2,0) -> 11.44114 | I50: =IF(I49>0,I49*0.2,0) -> 29.533696 | J50: =IF(J49>0,J49*0.2,0) -> 25.363699 | K50: =IF(K49>0,K49*0.2,0) -> 23.959594 | L50: =IF(L49>0,L49*0.2,0) -> 24.449806 | M50: =IF(M49>0,M49*0.2,0) -> 25.300822 | N50: =IF(N49>0,N49*0.2,0) -> 25.810838 | ... X50: =IF(X49>0,X49*0.2,0) -> 4.8680575
G51: =G49-G50 -> -25.0675 | H51: =H49-H50 -> 45.76456 | I51: =I49-I50 -> 118.13478 | J51: =J49-J50 -> 101.4548 | K51: =K49-K50 -> 95.838375 | L51: =L49-L50 -> 97.799223 | M51: =M49-M50 -> 101.20329 | N51: =N49-N50 -> 103.24335 | ... X51: =X49-X50 -> 19.47223
F52: Drug value
B56: Cash flow reconciliation
B57: Depreciation & Amort | D57: 4.55 | E57: 3.2 | F57: 2.91 | G57: 3 | H57: 3 | I57: 3 | J57: 3 | K57: 3 | L57: 3 | M57: 3 | N57: 3 | O57: 3 | P57: 3 | Q57: 3 | R57: 3 | S57: 3 | T57: 3 | U57: 3 | V57: 3 | W57: 3 | X57: 3
B58: Stock Based Comp | D58: 3 | E58: 4.768 | F58: 6.62 | G58: 8 | H58: =G58*1.02 -> 8.16 | I58: =H58*1.02 -> 8.3232 | J58: =I58*1.02 -> 8.489664 | K58: =J58*1.02 -> 8.6594573 | L58: =K58*1.02 -> 8.8326464 | M58: =L58*1.02 -> 9.0092994 | N58: =M58*1.02 -> 9.1894853 | O58: =N58*1.02 -> 9.373275 | P58: 5 | Q58: =P58*1.02 -> 5.1 | R58: =Q58*1.02 -> 5.202 | S58: =R58*1.02 -> 5.30604 | T58: =S58*1.02 -> 5.4121608 | U58: =T58*1.02 -> 5.520404 | V58: =U58*1.02 -> 5.6308121 | W58: =V58*1.02 -> 5.7434283 | X58: =W58*1.02 -> 5.8582969
B59: Capex | D59: 0.13 | E59: 0.331 | F59: 2.446 | G59: 5 | H59: 5
B60: Unlevered free cash flow | G60: =G45+G57+G58+G59 -> -11.3125 | H60: =H45+H57+H58+H59 -> 71.1207 | I60: =I45+I57+I58+I59 -> 156.74668 | J60: =J45+J57+J58+J59 -> 136.06316 | K60: =K45+K57+K58+K59 -> 129.21243 | L60: =L45+L57+L58+L59 -> 131.83667 | M60: =M45+M57+M58+M59 -> 134.51341 | N60: =N45+N57+N58+N59 -> 137.24368 | ... X60: =X45+X57+X58+X59 -> 29.198585
B62: Debt | F62: 18.96 | G62: 13 | H62: 13 | I62: 13 | J62: 13 | K62: 13 | L62: 13 | M62: 0 | N62: 0 | O62: 0 | P62: 0 | Q62: 0 | R62: 0 | S62: 0 | T62: 0 | U62: 0 | V62: 0 | W62: 0 | X62: 0
B63: TSO | D63: 17.72 | E63: 26.524 | F63: 45.644
F65: WACC
F66: Equity | G66: 2020 | H66: 2021 | I66: 2022 | J66: 2023 | K66: 2024
F67: Risk free rate | G67: 0.0089 | H67: 0.0145 | I67: 0.0295 | J67: 0.0396 | K67: 0.042
F68: Beta | G68: 1.7 | H68: 1.7 | I68: 1.7 | J68: 1.7 | K68: 1.7
F69: Equity Risk premium | G69: 0.0472 | H69: 0.0424 | I69: 0.0594 | J69: 0.046 | K69: 0.0433
F70: Cost of Equity | G70: =G67+G68*G69 -> 0.08914 | H70: =H67+H68*H69 -> 0.08658 | I70: =I67+I68*I69 -> 0.13048 | J70: =J67+J68*J69 -> 0.1178 | K70: =K67+K68*K69 -> 0.11561
K71: =AVERAGE(G70:K70) -> 0.107922
F73: Debt | G73: 2024 | I73: Equity | J73: 2024
F74: Total Debt | G74: =F62 -> 18.96 | I74: Current shares | J74: 48.53
F75: Debt Weight | G75: =G74/SUM(G74,J75) -> 0.069017459 | I75: Equity | J75: =IFERROR(__xludf.DUMMYFUNCTION("J74*googlefinance(""abeo"")"),255.7531) -> 255.7531
F76: Interest rate | G76: 0.135 | I76: Equity Weight | J76: =J75/SUM(J75,G74) -> 0.93098254
F77: Cost of debt | G77: =G76 -> 0.135 | I77: Cost of equity | J77: =K71 -> 0.107922
F78: WACC | G78: =G75*G76+J77*J76 -> 0.10979085
F79: WACC_2 | G79: 0.15
F80: WACC_3 | G80: 0.2
F82: DCF | G82: 2025 | H82: =G82+1 -> 2026 | I82: =H82+1 -> 2027 | J82: =I82+1 -> 2028 | K82: =J82+1 -> 2029 | L82: =K82+1 -> 2030 | M82: =L82+1 -> 2031 | N82: =M82+1 -> 2032 | O82: =N82+1 -> 2033 | ... X82: =W82+1 -> 2042
F83: r= 10.98% | G83: =G$60/((1+$G78)^(G$82-2024)) -> -10.193362 | H83: =H60/((1+$G$78)^(H82-2024)) -> 57.744914 | I83: =I60/((1+$G$78)^(I82-2024)) -> 114.67663 | J83: =J60/((1+$G$78)^(J82-2024)) -> 89.696602 | K83: =K60/((1+$G$78)^(K82-2024)) -> 76.753568 | L83: =L60/((1+$G$78)^(L82-2024)) -> 70.565007 | M83: =M60/((1+$G$78)^(M82-2024)) -> 64.875032 | N83: =N60/((1+$G$78)^(N82-2024)) -> 59.643512 | O83: =O60/((1+$G$78)^(O82-2024)) -> 40.481833 | ... X83: =X60/((1+$G$78)^(X82-2024)) -> 4.4773521
F84: r= 15% | G84: =G$60/((1+$G79)^(G$82-2024)) -> -9.8369565 | H84: =H$60/((1+$G79)^(H$82-2024)) -> 53.777467 | I84: =I$60/((1+$G79)^(I$82-2024)) -> 103.06349 | J84: =J$60/((1+$G79)^(J$82-2024)) -> 77.794554 | K84: =K$60/((1+$G79)^(K$82-2024)) -> 64.241412 | L84: =L$60/((1+$G79)^(L$82-2024)) -> 56.996633 | M84: =M$60/((1+$G79)^(M$82-2024)) -> 50.568573 | N84: =N$60/((1+$G79)^(N$82-2024)) -> 44.865201 | ... X84: =X$60/((1+$G79)^(X$82-2024)) -> 2.3593951
F85: r= 20% | G85: =G$60/((1+$G80)^(G$82-2024)) -> -9.4270833 | H85: =H$60/((1+$G80)^(H$82-2024)) -> 49.389375 | I85: =I$60/((1+$G80)^(I$82-2024)) -> 90.709884 | J85: =J$60/((1+$G80)^(J$82-2024)) -> 65.616879 | K85: =K$60/((1+$G80)^(K$82-2024)) -> 51.927576 | L85: =L$60/((1+$G80)^(L$82-2024)) -> 44.151836 | M85: =M$60/((1+$G80)^(M$82-2024)) -> 37.540224 | N85: =N$60/((1+$G80)^(N$82-2024)) -> 31.918493 | ... X85: =X$60/((1+$G80)^(X$82-2024)) -> 1.0967291
F87: Debt | G87: 18.96
F88: Cash | G88: 97.72
G90: DCF Fair value | H90: per share
F91: r= 10.98% | G91: =SUM(G83:X83)+$G$87-$G$88 -> 542.92482 | H91: =G91/48.5 -> 11.194326
F92: r= 15% | G92: =SUM(G84:X84)+$G$87-$G$88 -> 427.82906 | H92: =G92/48.5 -> 8.8212177
F93: r= 20% | G93: =SUM(G85:X85)+$G$87-$G$88 -> 323.56983 | H93: =G93/48.5 -> 6.6715429
F96: Multiples | G96: DCF Value | H96: EV-Peak Sales
F97: r= 10.97% | G97: =G91 -> 542.92482 | H97: =G97/MAX(G39:X39) -> 2.1290483
F98: r= 15% | G98: =G92 -> 427.82906 | H98: =G98/MAX(G39:X39) -> 1.677707
F99: r= 20% | G99: =G93 -> 323.56983 | H99: =G99/MAX(G39:X39) -> 1.2688604
F102: Implied probabiliity of approval
F105: Live net cash | G105: =80-19 -> 61
F106: Shares out. | G106: =48.53 -> 48.53
F107: Current price | G107: =IFERROR(__xludf.DUMMYFUNCTION("googlefinance(""ABEO"") "),5.27) -> 5.27
G109: DCF Fair value | H109: per share | I109: Implied probability
F110: r= 10.97% | G110: 549.15245 | H110: 11.322731 | I110: =($G$107-$G$105/$G$106)/(H110-$G$105/$G$106) -> 0.39868216
F111: r= 15% | G111: 427.82906 | H111: 8.8212177 | I111: =($G$107-$G$105/$G$106)/(H111-$G$105/$G$106) -> 0.53052695
F112: r= 20% | G112: 323.56983 | H112: 6.6715429 | I112: =($G$107-$G$105/$G$106)/(H112-$G$105/$G$106) -> 0.7411543

Sheet risk adjusted post approval 
A1: Research
B3: RDEB All | C3: Prevalence / mn | D3: Incidence /mn | E3: US pop mn | F3: Patient pop | G3: Notes
B4: Eichstadt et al (2019) | C4: =12562/340 -> 36.947059 | D4: 95 | E4: 340 | F4: =C4*E4 -> 12562 | G4: Unreliable genetic model
B5: Prop. Claims analysis (Abeona) | C5: =750/E5 -> 2.2058824 | D5: NA | E5: 340 | F5: 750 | G5: Method unavailable
A6: > | B6: Fine et al | C6: 1.35 | D6: 3.05 | E6: 340 | F6: =C6*E6 -> 459 | G6: NEBR data, most commonly cited
A7: > | B7: Baardman et al | C7: 2.1 | D7: 5.5 | E7: 340 | F7: =E7*C7 -> 714 | G7: Dutch EB registry
B8: Kim et al | E8: 340
A9: > | B9: Petrof et al | C9: 3.3 | D9: 8.1 | E9: 340 | F9: =C9*E9 -> 1122 | G9: NHS England and Wales
B10: Average | C10: =AVERAGE(C6:C9) -> 2.25 | D10: =AVERAGE(D6:D9) -> 5.55 | F10: =AVERAGE(F6:F9) -> 765
B12: RDEB patient "churn rate" | C12: =(D10*3.6)/F10 -> 0.026117647
B13: Implied life expectancy | C13: =1/C12 -> 38.288288
B14: Assuming 3.6 million live births
I15: (approval)
B16: Competition | C16: Vyjuvek | E16: KRYS valuation | H16: KRYS uptake | I16: Q2 2023 | J16: Q3 2023 | K16: Q4 2023 | L16: Q1 2024 | M16: Q2 2024 | N16: Q3 2024 | O16: Q4 2024
B17: Marketing auth holder | C17: KRYS | E17: MC | F17: =IFERROR(__xludf.DUMMYFUNCTION("googlefinance(""KRYS"",""marketcap"")/1000000"),3953.301208) -> 3953.3012 | G17: M | H17: Revenue | J17: 8.6 | K17: 42.1 | L17: 45.3 | M17: 70.3 | N17: 83.8 | O17: 91.1
B18: annualised sales (ASP) | C18: =91.1 * 4 -> 364.4 | E18: Cash | F18: 597.5 | G18: M | H18: Patients treated | J18: =J17*1000000/($F$21/4) -> 68.690967 | K18: =K17*1000000/($F$21/4) -> 336.26624 | L18: =L17*1000000/($F$21/4) -> 361.82567 | M18: =M17*1000000/($F$21/4) -> 561.50872 | N18: =N17*1000000/($F$21/4) -> 669.33756 | O18: =O17*1000000/($F$21/4) -> 727.64501
B19: Sales (retail) | C19: =C18*1.26 -> 459.144 | E19: EV | F19: =F17-F18 -> 3355.8012 | G19: M | H19: patient pop | J19: =$C$23 -> 1108.4 | K19: =$C$23 -> 1108.4 | L19: =$C$23 -> 1108.4 | M19: =$C$23 -> 1108.4 | N19: =$C$23 -> 1108.4 | O19: =$C$23 -> 1108.4
B20: Pricing (list) - patient year | C20: 631000 | E20: Peak sales | F20: =F21*F22/1000000 -> 628.27586 | G20: M | H20: % of peak | J20: =J18/J19 -> 0.061973084 | K20: =K18/K19 -> 0.30337987 | L20: =L18/L19 -> 0.32643962 | M20: =M18/M19 -> 0.50659393 | N20: =N18/N19 -> 0.60387726 | O20: =O18/O19 -> 0.65648232
B21: Patients | C21: =C19*1000000/C20 -> 727.64501 | E21: ASP/patient y | F21: =C18*1000000/C21 -> 500793.65 | G21: $ | O21: quick uptake
A22: 4y ramp | B22: Peak patients | C22: =C21/0.58 -> 1254.5604 | D22: RDEB + DDEB | E22: Peak patients | F22: =C22 -> 1254.5604
A23: sanity check | B23: DEB prevalence (JD Fine) | C23: =340*3.26 -> 1108.4 | E23: EV-Peak sales | F23: =F19/F20 -> 5.3412862 | G23: x
E24: EV-Sales | F24: =F19/C18 -> 9.2091142 | G24: x
A26: Model | B26: rNPV
Q27: check patent expiry date ...
C28: 2022 | D28: 2023 | E28: 2024 | F28: 2025 | G28: =F28+1 -> 2026 | H28: =G28+1 -> 2027 | I28: =H28+1 -> 2028 | J28: =I28+1 -> 2029 | K28: =J28+1 -> 2030 | L28: =K28+1 -> 2031 | M28: =L28+1 -> 2032 | N28: =M28+1 -> 2033 | ... W28: =V28+1 -> 2042
B29: US population | F29: 340 | G29: 340 | H29: 340 | I29: 340 | J29: 340 | K29: 340 | L29: 340 | M29: 340 | N29: 340 | O29: 340 | P29: 340 | Q29: 340 | R29: 340 | S29: 340 | T29: 340 | U29: 340 | V29: 340 | W29: 340
B30: Prevalence | F30: =AVERAGE($C$9,$C$7,$C$6) -> 2.25 | G30: =AVERAGE($C$9,$C$7,$C$6) -> 2.25 | H30: =AVERAGE($C$9,$C$7,$C$6) -> 2.25 | I30: =AVERAGE($C$9,$C$7,$C$6) -> 2.25 | J30: =AVERAGE($C$9,$C$7,$C$6) -> 2.25 | K30: =AVERAGE($C$9,$C$7,$C$6) -> 2.25 | L30: =AVERAGE($C$9,$C$7,$C$6) -> 2.25 | M30: =AVERAGE($C$9,$C$7,$C$6) -> 2.25 | ... W30: =AVERAGE($C$9,$C$7,$C$6) -> 2.25
B31: Patient population | F31: =F29*F30 -> 765 | G31: =G29*G30 -> 765 | H31: =H29*H30 -> 765 | I31: =I29*I30 -> 765 | J31: =J29*J30 -> 765 | K31: =K29*K30 -> 765 | L31: =L29*L30 -> 765 | M31: =M29*M30 -> 765 | ... W31: =W29*W30 -> 765
B32: US Live births | F32: 3.6 | G32: 3.6 | H32: 3.6 | I32: 3.6 | J32: 3.6 | K32: 3.6 | L32: 3.6 | M32: 3.6 | N32: 3.6 | O32: 3.6 | P32: 3.6 | Q32: 3.6 | R32: 3.6 | S32: 3.6 | T32: 3.6 | U32: 3.6 | V32: 3.6 | W32: 3.6
B33: Incidence /mn | F33: 5.55 | G33: 5.55 | H33: 5.55 | I33: 5.55 | J33: 5.55 | K33: 5.55 | L33: 5.55 | M33: 5.55 | N33: 5.55 | O33: 5.55 | P33: 5.55 | Q33: 5.55 | R33: 5.55 | S33: 5.55 | T33: 5.55 | U33: 5.55 | V33: 5.55 | W33: 5.55
B34: Incidence total | F34: =F33*F32 -> 19.98 | G34: =G33*G32 -> 19.98 | H34: =H33*H32 -> 19.98 | I34: =I33*I32 -> 19.98 | J34: =J33*J32 -> 19.98 | K34: =K33*K32 -> 19.98 | L34: =L33*L32 -> 19.98 | M34: =M33*M32 -> 19.98 | ... W34: =W33*W32 -> 19.98
B35: BOP treatment opportunities | F35: =F31*0.8 -> 612 | G35: =F35-F36+G34*0.8 -> 617.984 | H35: =G35-G36+H34*0.8 -> 583.968 | I35: =H35-H36+I34*0.8 -> 479.952 | J35: =I35-I36+J34*0.8 -> 375.936 | K35: =J35-J36+K34*0.8 -> 271.92 | L35: =K35-K36+L34*0.8 -> 15.984 | M35: =L35-L36+M34*0.8 -> 15.984 | N35: =M35-M36+N34*0.8 -> 15.984 | ... W35: =V35-V36+W34*0.8 -> 15.984
B36: treatments administered | F36: 10 | G36: 50 | H36: 120 | I36: 120 | J36: 120 | K36: =K35 -> 271.92 | L36: =L35 -> 15.984 | M36: =M35 -> 15.984 | N36: =N35 -> 15.984 | O36: =O35 -> 15.984 | P36: =P35 -> 15.984 | Q36: =Q35 -> 15.984 | R36: =R35 -> 15.984 | ... W36: =W35 -> 15.984
B37: Price per treatment | F37: 3100000 | G37: =F37*1.02 -> 3162000 | H37: =G37*1.02 -> 3225240 | I37: =H37*1.02 -> 3289744.8 | J37: =I37*1.02 -> 3355539.7 | K37: =J37*1.02 -> 3422650.5 | L37: =K37*1.02 -> 3491103.5 | M37: =L37*1.02 -> 3560925.6 | N37: =M37*1.02 -> 3632144.1 | ... W37: =V37*1.02 -> 4340748.4
B38: Price (ASP) | F38: =F37*0.74 -> 2294000 | G38: =G37*0.74 -> 2339880 | H38: =H37*0.74 -> 2386677.6 | I38: =I37*0.74 -> 2434411.2 | J38: =J37*0.74 -> 2483099.4 | K38: =K37*0.74 -> 2532761.4 | L38: =L37*0.74 -> 2583416.6 | M38: =M37*0.74 -> 2635084.9 | ... W38: =W37*0.74 -> 3212153.8
A39: =SUM(G39:W39) -> 2236.0349 | B39: Revenue | F39: =F36*F38/1000000 -> 22.94 | G39: =G36*G38/1000000 -> 116.994 | H39: =H36*H38/1000000 -> 286.40131 | I39: =I36*I38/1000000 -> 292.12934 | J39: =J36*J38/1000000 -> 297.97193 | K39: =K36*K38/1000000 -> 688.70847 | L39: =L36*L38/1000000 -> 41.293331 | M39: =M36*M38/1000000 -> 42.119197 | ... W39: =W36*W38/1000000 -> 51.343067
B40: COGS | F40: =F39*0.15 -> 3.441 | G40: =G39*0.15 -> 17.5491 | H40: =H39*0.15 -> 42.960197 | I40: =I39*0.15 -> 43.819401 | J40: =J39*0.15 -> 44.695789 | K40: =K39*0.15 -> 103.30627 | L40: =L39*0.15 -> 6.1939996 | M40: =M39*0.15 -> 6.3178796 | ... W40: =W39*0.15 -> 7.70146
B41: Gross profit | F41: =F39-F40 -> 19.499 | G41: =G39-G40 -> 99.4449 | H41: =H39-H40 -> 243.44112 | I41: =I39-I40 -> 248.30994 | J41: =J39-J40 -> 253.27614 | K41: =K39-K40 -> 585.4022 | L41: =L39-L40 -> 35.099331 | M41: =M39-M40 -> 35.801318 | ... W41: =W39-W40 -> 43.641607
B42: (risk adjusted gross profit) | F42: =F41*0.5*0.43 +F41*0.5 -> 13.941785 | G42: =G41*0.5*0.43 +G41*0.5 -> 71.103104 | H42: =H41*0.5*0.43 +H41*0.5 -> 174.0604 | I42: =I41*0.5*0.43 +I41*0.5 -> 177.54161 | J42: =J41*0.5*0.43 +J41*0.5 -> 181.09244 | K42: =K41*0.5*0.43 +K41*0.5 -> 418.56257 | L42: =L41*0.5*0.43 +L41*0.5 -> 25.096022 | M42: =M41*0.5*0.43 +M41*0.5 -> 25.597942 | ... W42: =W41*0.5*0.43 +W41*0.5 -> 31.203749
B44: R&D | C44: 28.97 | D44: 31.09 | E44: 34.36 | F44: 5 | G44: 5 | H44: 5 | I44: 5 | J44: 5 | K44: 5 | L44: 5 | M44: 5 | N44: 5 | O44: 5 | P44: 5 | Q44: 5 | R44: 5 | S44: 5 | T44: 5 | U44: 5 | V44: 5 | W44: 5
B45: General & Administrative | C45: 17.26 | D45: 19 | E45: 29.85 | F45: =136*1.5*0.225 -> 45.9 | G45: =136*1.5*0.225 -> 45.9 | H45: =136*1.5*0.225 -> 45.9 | I45: =I39*0.3 -> 87.638801 | J45: =J39*0.34 -> 101.31045 | K45: =K39*0.34 -> 234.16088 | L45: =L39*0.34 -> 14.039732 | M45: =M39*0.34 -> 14.320527 | N45: =N39*0.34 -> 14.606938 | O45: =O39*0.34 -> 14.899076 | P45: =P39*0.34 -> 15.197058 | Q45: =Q39*0.34 -> 15.500999 | ... W45: =W39*0.34 -> 17.456643
B46: EBIT | F46: =F41-F44-F45 -> -31.401 | G46: =G41-G44-G45 -> 48.5449 | H46: =H41-H44-H45 -> 192.54112 | I46: =I41-I44-I45 -> 155.67114 | J46: =J41-J44-J45 -> 146.96568 | K46: =K41-K44-K45 -> 346.24132 | L46: =L41-L44-L45 -> 16.059599 | M46: =M41-M44-M45 -> 16.480791 | ... W46: =W41-W44-W45 -> 21.184964
B47: (risk adjuted EBIT) | F47: =F42-F44-F45 -> -36.958215 | G47: =G42-G44-G45 -> 20.203104 | H47: =H42-H44-H45 -> 123.1604 | I47: =I42-I44-I45 -> 84.902804 | J47: =J42-J44-J45 -> 74.781983 | K47: =K42-K44-K45 -> 179.40169 | L47: =L42-L44-L45 -> 6.0562893 | M47: =M42-M44-M45 -> 6.2774151 | ... W47: =W42-W44-W45 -> 8.7471061
B48: Interest Income | C48: 0.431 | D48: 2.117 | E48: 4.25 | F48: 4 | G48: 4 | H48: 4 | I48: 4 | J48: 4 | K48: 4 | L48: 4 | M48: 4 | N48: 4 | O48: 4 | P48: 4 | Q48: 4 | R48: 4 | S48: 4 | T48: 4 | U48: 4 | V48: 4 | W48: 4
B49: Interest Expense | E49: 4.208 | F49: =F50*F70 -> 1.755 | G49: =G50*G70 -> 1.755 | H49: =H50*H70 -> 1.755 | I49: =I50*I70 -> 1.755 | J49: =J50*J70 -> 1.755 | K49: =K50*K70 -> 1.755 | L49: =L50*L70 -> 0 | M49: =M50*M70 -> 0 | ... W49: =W50*W70 -> 0
B50: Effective borrow rate | E50: =E49/E70 -> 0.22194093 | F50: 0.135 | G50: 0.135 | H50: 0.135 | I50: 0.135 | J50: 0.135 | K50: 0.135 | L50: 0.135 | M50: 0.135 | N50: 0.135 | O50: 0.135 | P50: 0.135 | Q50: 0.135 | R50: 0.135 | S50: 0.135 | T50: 0.135 | U50: 0.135 | V50: 0.135 | W50: 0.135
B51: EBT | F51: =F46+F48-F49 -> -29.156 | G51: =G46+G48-G49 -> 50.7899 | H51: =H46+H48-H49 -> 194.78612 | I51: =I46+I48-I49 -> 157.91614 | J51: =J46+J48-J49 -> 149.21068 | K51: =K46+K48-K49 -> 348.48632 | L51: =L46+L48-L49 -> 20.059599 | M51: =M46+M48-M49 -> 20.480791 | ... W51: =W46+W48-W49 -> 25.184964
B52: (risk adjusted EBT) | F52: =F47+F48-F49 -> -34.713215 | G52: =G47+G48-G49 -> 22.448104 | H52: =H47+H48-H49 -> 125.4054 | I52: =I47+I48-I49 -> 87.147804 | J52: =J47+J48-J49 -> 77.026983 | K52: =K47+K48-K49 -> 181.64669 | L52: =L47+L48-L49 -> 10.056289 | M52: =M47+M48-M49 -> 10.277415 | ... W52: =W47+W48-W49 -> 12.747106
B53: Tax | F53: =IF(F51>0,F51*0.2,0) -> 0 | G53: =IF(G51>0,G51*0.2,0) -> 10.15798 | H53: =IF(H51>0,H51*0.2,0) -> 38.957223 | I53: =IF(I51>0,I51*0.2,0) -> 31.583227 | J53: =IF(J51>0,J51*0.2,0) -> 29.842136 | K53: =IF(K51>0,K51*0.2,0) -> 69.697264 | L53: =IF(L51>0,L51*0.2,0) -> 4.0119197 | M53: =IF(M51>0,M51*0.2,0) -> 4.0961581 | ... W53: =IF(W51>0,W51*0.2,0) -> 5.0369928
B54: (tax for risk adjusted EBT) | F54: =IF(F52>0,F52*0.2,0) -> 0 | G54: =IF(G52>0,G52*0.2,0) -> 4.4896207 | H54: =IF(H52>0,H52*0.2,0) -> 25.081079 | I54: =IF(I52>0,I52*0.2,0) -> 17.429561 | J54: =IF(J52>0,J52*0.2,0) -> 15.405397 | K54: =IF(K52>0,K52*0.2,0) -> 36.329339 | L54: =IF(L52>0,L52*0.2,0) -> 2.0112579 | M54: =IF(M52>0,M52*0.2,0) -> 2.055483 | ... W54: =IF(W52>0,W52*0.2,0) -> 2.5494212
B55: Net profit | F55: =F51-F53 -> -29.156 | G55: =G51-G53 -> 40.63192 | H55: =H51-H53 -> 155.82889 | I55: =I51-I53 -> 126.33291 | J55: =J51-J53 -> 119.36855 | K55: =K51-K53 -> 278.78906 | L55: =L51-L53 -> 16.047679 | M55: =M51-M53 -> 16.384633 | ... W55: =W51-W53 -> 20.147971
B56: (Risk adjusted net profit) | F56: =F52-F54 -> -34.713215 | G56: =G52-G54 -> 17.958483 | H56: =H52-H54 -> 100.32432 | I56: =I52-I54 -> 69.718243 | J56: =J52-J54 -> 61.621586 | K56: =K52-K54 -> 145.31735 | L56: =L52-L54 -> 8.0450315 | M56: =M52-M54 -> 8.2219321 | ... W56: =W52-W54 -> 10.197685
D58: sanity check | E58: NPV | F58: {=NPV(0.19,F55:W55)} -> 335.96778
E59: rNPV | F59: {=NPV(0.19,F56:W56)} -> 168.94766
E60: Shares | F60: 48.53
E61: FV | F61: =(F58+F101-F100)/F60 -> 10.693752 | G61: =(F59+F101-F100)/F60 -> 7.2521669
E62: Current price | F62: 6.22
B63: Cash flow reconciliation
B64: Depreciation & Amort | C64: 4.55 | D64: 3.2 | E64: 2.91 | F64: 3 | G64: 3 | H64: 3 | I64: 3 | J64: 3 | K64: 3 | L64: 3 | M64: 3 | N64: 3 | O64: 3 | P64: 3 | Q64: 3 | R64: 3 | S64: 3 | T64: 3 | U64: 3 | V64: 3 | W64: 3
B65: Stock Based Comp | C65: 3 | D65: 4.768 | E65: 6.62 | F65: 8 | G65: =F65*1.02 -> 8.16 | H65: =G65*1.02 -> 8.3232 | I65: =H65*1.02 -> 8.489664 | J65: =I65*1.02 -> 8.6594573 | K65: =J65*1.02 -> 8.8326464 | L65: =K65*1.02 -> 9.0092994 | M65: =L65*1.02 -> 9.1894853 | N65: =M65*1.02 -> 9.373275 | O65: 5 | P65: =O65*1.02 -> 5.1 | Q65: =P65*1.02 -> 5.202 | R65: =Q65*1.02 -> 5.30604 | S65: =R65*1.02 -> 5.4121608 | T65: =S65*1.02 -> 5.520404 | U65: =T65*1.02 -> 5.6308121 | V65: =U65*1.02 -> 5.7434283 | W65: =V65*1.02 -> 5.8582969
B66: Capex | C66: 0.13 | D66: 0.331 | E66: 2.446 | F66: 5 | G66: 5
B67: Unlevered free cash flow | F67: =F46-F53+F64+F65+F66 -> -15.401 | G67: =G46-G53+G64+G65+G66 -> 54.54692 | H67: =H46-H53+H64+H65+H66 -> 164.90709 | I67: =I46-I53+I64+I65+I66 -> 135.57757 | J67: =J46-J53+J64+J65+J66 -> 128.783 | K67: =K46-K53+K64+K65+K66 -> 288.3767 | L67: =L46-L53+L64+L65+L66 -> 24.056978 | M67: =M46-M53+M64+M65+M66 -> 24.574118 | ... W67: =W46-W53+W64+W65+W66 -> 25.006268
B68: rFCFF | F68: =F47-F54+F64+F65+F66 -> -20.958215 | G68: =G47-G54+G64+G65+G66 -> 31.873483 | H68: =H47-H54+H64+H65+H66 -> 109.40252 | I68: =I47-I54+I64+I65+I66 -> 78.962907 | J68: =J47-J54+J64+J65+J66 -> 71.036044 | K68: =K47-K54+K64+K65+K66 -> 154.905 | L68: =L47-L54+L64+L65+L66 -> 16.054331 | M68: =M47-M54+M64+M65+M66 -> 16.411417 | ... W68: =W47-W54+W64+W65+W66 -> 15.055982
B70: Debt | E70: 18.96 | F70: 13 | G70: 13 | H70: 13 | I70: 13 | J70: 13 | K70: 13 | L70: 0 | M70: 0 | N70: 0 | O70: 0 | P70: 0 | Q70: 0 | R70: 0 | S70: 0 | T70: 0 | U70: 0 | V70: 0 | W70: 0
B71: TSO | C71: 17.72 | D71: 26.524 | E71: 45.644
E73: WACC
E74: Equity | F74: 2020 | G74: 2021 | H74: 2022 | I74: 2023 | J74: 2024
E75: Risk free rate | F75: 0.0089 | G75: 0.0145 | H75: 0.0295 | I75: 0.0396 | J75: 0.042
E76: Beta | F76: 0.94 | G76: 0.94 | H76: 0.94 | I76: 0.94 | J76: 0.94
E77: Equity Risk premium | F77: 0.0472 | G77: 0.0424 | H77: 0.0594 | I77: 0.046 | J77: 0.0433
E78: Cost of Equity | F78: =F75+F76*F77 -> 0.053268 | G78: =G75+G76*G77 -> 0.054356 | H78: =H75+H76*H77 -> 0.085336 | I78: =I75+I76*I77 -> 0.08284 | J78: =J75+J76*J77 -> 0.082702
J79: =AVERAGE(F78:J78) -> 0.0717004
E81: Debt | F81: 2024 | H81: Equity | I81: 2024
E82: Total Debt | F82: =E70 -> 18.96 | H82: Current shares | I82: 48.53
E83: Debt Weight | F83: =F82/SUM(F82,I83) -> 0.069017459 | H83: Equity | I83: =IFERROR(__xludf.DUMMYFUNCTION("J74*googlefinance(""abeo"")"),255.7531) -> 255.7531
E84: Interest rate | F84: 0.135 | H84: Equity Weight | I84: =I83/SUM(I83,F82) -> 0.93098254
E85: Cost of debt | F85: =F84 -> 0.135 | H85: Cost of equity | I85: =J79 -> 0.0717004
E86: WACC | F86: =F83*F84+I85*I84 -> 0.076069178
E87: WACC_2 | F87: 0.15
E88: WACC_3 | F88: 0.2
E90: DCF | F90: 2025 | G90: =F90+1 -> 2026 | H90: =G90+1 -> 2027 | I90: =H90+1 -> 2028 | J90: =I90+1 -> 2029 | K90: =J90+1 -> 2030 | L90: =K90+1 -> 2031 | M90: =L90+1 -> 2032 | N90: =M90+1 -> 2033 | ... W90: =V90+1 -> 2042
E91: r= 7.61% | F91: =F$67/((1+$F$86)^(F$90-2024)) -> -14.312277 | G91: =G67/((1+$F$86)^(G90-2024)) -> 47.107478 | H91: =H67/((1+$F$86)^(H90-2024)) -> 132.34842 | I91: =I67/((1+$F$86)^(I90-2024)) -> 101.11768 | J91: =J67/((1+$F$86)^(J90-2024)) -> 89.260145 | K91: =K67/((1+$F$86)^(K90-2024)) -> 185.74581 | L91: =L67/((1+$F$86)^(L90-2024)) -> 14.399909 | M91: =M67/((1+$F$86)^(M90-2024)) -> 13.669619 | N91: =N67/((1+$F$86)^(N90-2024)) -> 12.975966 | ... W91: =W67/((1+$F$86)^(W90-2024)) -> 6.6822917
E92: r= 15% | F92: =F$67/((1+$F87)^(F$90-2024)) -> -13.392174 | G92: =G$67/((1+$F87)^(G$90-2024)) -> 41.245308 | H92: =H$67/((1+$F87)^(H$90-2024)) -> 108.42909 | I92: =I$67/((1+$F87)^(I$90-2024)) -> 77.516917 | J92: =J$67/((1+$F87)^(J$90-2024)) -> 64.027913 | K92: =K$67/((1+$F87)^(K$90-2024)) -> 124.67321 | L92: =L$67/((1+$F87)^(L$90-2024)) -> 9.0439092 | M92: =M$67/((1+$F87)^(M$90-2024)) -> 8.0333227 | ... W92: =W$67/((1+$F87)^(W$90-2024)) -> 2.0206345
E93: r= 20% | F93: =F$67/((1+$F88)^(F$90-2024)) -> -12.834167 | G93: =G$67/((1+$F88)^(G$90-2024)) -> 37.879806 | H93: =H$67/((1+$F88)^(H$90-2024)) -> 95.432345 | I93: =I$67/((1+$F88)^(I$90-2024)) -> 65.382703 | J93: =J$67/((1+$F88)^(J$90-2024)) -> 51.755 | K93: =K$67/((1+$F88)^(K$90-2024)) -> 96.576774 | L93: =L$67/((1+$F88)^(L$90-2024)) -> 6.7138611 | M93: =M$67/((1+$F88)^(M$90-2024)) -> 5.7151544 | ... W93: =W$67/((1+$F88)^(W$90-2024)) -> 0.93926135
E95: risk adjusted | F95: 2025 | G95: =F95+1 -> 2026 | H95: =G95+1 -> 2027 | I95: =H95+1 -> 2028 | J95: =I95+1 -> 2029 | K95: =J95+1 -> 2030 | L95: =K95+1 -> 2031 | M95: =L95+1 -> 2032 | N95: =M95+1 -> 2033 | ... W95: =V95+1 -> 2042
E96: r= 7.61% | F96: =F$68/((1+$F$86)^(F$90-2024)) -> -19.476643 | G96: =G$68/((1+$F$86)^(G95-2024)) -> 27.526382 | H96: =H$68/((1+$F$86)^(H95-2024)) -> 87.802472 | I96: =I$68/((1+$F$86)^(I95-2024)) -> 58.892822 | J96: =J$68/((1+$F$86)^(J95-2024)) -> 49.235438 | K96: =K$68/((1+$F$86)^(K95-2024)) -> 99.775586 | L96: =L$68/((1+$F$86)^(L95-2024)) -> 9.6097229 | M96: =M$68/((1+$F$86)^(M95-2024)) -> 9.1290284 | N96: =N$68/((1+$F$86)^(N95-2024)) -> 8.6719651 | ... W96: =W$68/((1+$F$86)^(W95-2024)) -> 4.0233297
E97: r= 15% | F97: =F$68/((1+$F87)^(F$95-2024)) -> -18.224535 | G97: =G$68/((1+$F87)^(G$95-2024)) -> 24.100932 | H97: =H$68/((1+$F87)^(H$95-2024)) -> 71.933931 | I97: =I$68/((1+$F87)^(I$95-2024)) -> 45.147298 | J97: =J$68/((1+$F87)^(J$95-2024)) -> 35.317468 | K97: =K$68/((1+$F87)^(K$95-2024)) -> 66.969707 | L97: =L$68/((1+$F87)^(L$95-2024)) -> 6.0354176 | M97: =M$68/((1+$F87)^(M$95-2024)) -> 5.3649215 | ... W97: =W$68/((1+$F87)^(W$95-2024)) -> 1.2166004
E98: r= 20% | F98: =F$68/((1+$F88)^(F$95-2024)) -> -17.465179 | G98: =G$68/((1+$F88)^(G$95-2024)) -> 22.134363 | H98: =H$68/((1+$F88)^(H$95-2024)) -> 63.311642 | I98: =I$68/((1+$F88)^(I$95-2024)) -> 38.080106 | J98: =J$68/((1+$F88)^(J$95-2024)) -> 28.547793 | K98: =K$68/((1+$F88)^(K$95-2024)) -> 51.877371 | L98: =L$68/((1+$F88)^(L$95-2024)) -> 4.4804691 | M98: =M$68/((1+$F88)^(M$95-2024)) -> 3.8167712 | ... W98: =W$68/((1+$F88)^(W$95-2024)) -> 0.56551828
E100: Debt | F100: =cover!C9 -> 24.1
E101: Cash | F101: =cover!C8 -> 207.1 | G101: live cash est. bpc
E102: current EV | F102: =cover!C7- F101+F100 -> 82.668
F104: Equity Value | G104: per share
E105: r= 7.61% | F105: =SUM(F91:W91)-$F$100+$F$101 -> 840.02572 | G105: =F105/48.5 -> 17.320118
E106: r= 15% | F106: =SUM(F92:W92)-$F$100+$F$101 -> 640.30378 | G106: =F106/48.5 -> 13.20214
E107: r= 20% | F107: =SUM(F93:W93)-$F$100+$F$101 -> 552.00831 | G107: =F107/48.5 -> 11.381615
E109: Risk adjusted | F109: Equity value | G109: per share
E110: r= 7.61% | F110: =SUM(F96:W96)-$F$100+$F$101 -> 558.95352 | G110: =F110/48.5 -> 11.524815 | H110: <
E111: r= 15% | F111: =SUM(F97:W97)-$F$100+$F$101 -> 442.74332 | G111: =F111/48.5 -> 9.1287282
E112: r= 20% | F112: =SUM(F98:W98)-$F$100+$F$101 -> 391.53054 | G112: =F112/48.5 -> 8.0727947
